commons/__init__.py
commons/converters.py
commons/openpyxl_wo_formatting.py
commons/utils.py
loader/__init__.py
loader/loader.py
models/__init__.py
models/assets.py
models/photos.py
models/systems.py
xlsmloader-1.0.2.dist-info/LICENSE
xlsmloader-1.0.2.dist-info/METADATA
xlsmloader-1.0.2.dist-info/WHEEL
xlsmloader-1.0.2.dist-info/entry_points.txt
xlsmloader-1.0.2.dist-info/top_level.txt
xlsmloader-1.0.2.dist-info/RECORD
