Metadata-Version: 2.1
Name: xlsmloader
Version: 1.0.2
Home-page: https://xlsmloader.pypa.io/
Author: Paulo Rogerio Sales Santos
Author-email: Paulo Rogério Sales Santos <paulosales@gmail.com>
License: Copyright 2023 Paulo Rogério Sales Santos - paulosales@gmail.com
Keywords: xlsm,reader,assets,sql
Requires-Python: >=3.7
License-File: LICENSE
Requires-Dist: et-xmlfile (>=1.1.0)
Requires-Dist: numpy (>=1.24.2)
Requires-Dist: openpyxl (>=3.1.0)
Requires-Dist: pandas (>=1.5.3)
Requires-Dist: python-dateutil (>=2.8.2)
Requires-Dist: pytz (>=2022.7.1)
Requires-Dist: six (>=1.16.0)
Requires-Dist: tomli ; python_version < "3.11"
